{
  "statuses": [
    {
      "id": "Poison",
      "name": "Poison",
      "successRatePercent": 30,
      "description": "Damages at the end of every turn. (wears off).",
      "statusType": 0,
      "applyMoment": 0,
      "applyType": 0,
      "statName": 1,
      "powerPercent": -10,
      "maxTurns": "3",
      "blockedByStatuses": [
        "Petrified",
        "Venom",
        "Toxic"
      ]
    },
    {
      "id": "Toxic",
      "name": "Toxic",
      "successRatePercent": 30,
      "description": "Greatly Damages at the end of every turn (wears off).",
      "statusType": 0,
      "applyMoment": 0,
      "applyType": 0,
      "statName": 1,
      "powerPercent": -20,
      "maxTurns": "3",
      "removesStatusesOnAdd": [
        "Poison"
      ],
      "blockedByStatuses": [
        "Petrified",
        "Venom"
      ]
    },
    {
      "id": "Venom",
      "name": "Venom",
      "successRatePercent": 30,
      "description": "Greatly Damages at the end of every turn",
      "statusType": 0,
      "applyMoment": 0,
      "applyType": 0,
      "statName": 1,
      "powerPercent": -20,
      "maxTurns": "999",
      "removesStatusesOnAdd": [
        "Poison",
        "Toxic"
      ],
      "blockedByStatuses": [
        "Petrified"
      ]
    },
    {
      "id": "Regen",
      "name": "Regen",
      "successRatePercent": 100,
      "description": "Resplenishes character's HP every turn",
      "statusType": 1,
      "applyMoment": 0,
      "applyType": 0,
      "statName": 1,
      "powerPercent": 20,
      "maxTurns": "3",
      "blockedByStatuses": [
        "Petrified"
      ]
    },
    {
      "id": "RegenM",
      "name": "RegenM",
      "successRatePercent": 100,
      "description": "Refills character's MP every turn",
      "statusType": 1,
      "applyMoment": 0,
      "applyType": 0,
      "statName": 1,
      "powerPercent": 5,
      "maxTurns": "3",
      "blockedByStatuses": [
        "Petrified"
      ]
    },
    {
      "id": "Sleep",
      "name": "Sleep",
      "successRatePercent": 30,
      "description": "Prevents all actions (wears off or get hit).",
      "statusType": 0,
      "applyMoment": 1,
      "applyType": 1,
      "statName": 10,
      "powerPercent": 0,
      "maxTurns": "999",
      "removesStatusesOnAdd": [
        "Berserk"
      ],
      "blockedByStatuses": [
        "Freeze",
        "Petrified"
      ]
    },
    {
      "id": "Freeze",
      "name": "Freeze",
      "successRatePercent": 30,
      "description": "Prevents all actions (wears off).",
      "statusType": 0,
      "applyMoment": 1,
      "applyType": 1,
      "statName": 10,
      "powerPercent": 0,
      "maxTurns": "999",
      "removesStatusesOnAdd": [
        "Berserk",
        "Sleep"
      ],
      "blockedByStatuses": [
        "Petrified"
      ]
    },
    {
      "id": "Petrified",
      "name": "Petrified",
      "successRatePercent": 30,
      "description": "Prevents all actions, kills character after three turns if not cured.",
      "statusType": 0,
      "applyMoment": 1,
      "applyType": 1,
      "statName": 10,
      "powerPercent": 0,
      "maxTurns": "3",
      "removesStatusesOnAdd": [
        "Berserk",
        "Sleep"
      ]
    },
    {
      "id": "Berserk",
      "name": "Berserk",
      "successRatePercent": 30,
      "description": "Attacks a random target with increased strength",
      "statusType": 0,
      "applyMoment": 1,
      "applyType": 1,
      "statName": 10,
      "powerPercent": 0,
      "maxTurns": "999",
      "removesStatusesOnAdd": [
        "Freeze"
      ],
      "blockedByStatuses": [
        "Sleep",
        "Freeze",
        "Petrified"
      ]
    },
    {
      "id": "Mute",
      "name": "Mute",
      "successRatePercent": 30,
      "description": "Prevents magic casting.",
      "statusType": 0,
      "applyMoment": 1,
      "applyType": 2,
      "statName": 10,
      "powerPercent": 0,
      "maxTurns": "3",
      "blockedByStatuses": [
        "Sleep",
        "Freeze",
        "Petrified"
      ]
    },
    {
      "id": "Martyr",
      "name": "Martyr",
      "successRatePercent": 30,
      "description": "Triples the chance to inflict critical hit damage. Kill character after three turns if fight is not over",
      "statusType": 0,
      "applyMoment": 1,
      "applyType": 3,
      "statName": 9,
      "powerPercent": 300,
      "maxTurns": "3",
      "blockedByStatuses": [
        "Sleep",
        "Freeze",
        "Petrified"
      ]
    },
    {
      "id": "Heavy",
      "name": "Heavy",
      "successRatePercent": 100,
      "description": "Reduces character's ability to evade physical attacks.",
      "statusType": 0,
      "applyMoment": 1,
      "applyType": 3,
      "statName": 7,
      "powerPercent": -30,
      "maxTurns": "3",
      "removesStatusesOnAdd": [
        "Light"
      ],
      "blockedByStatuses": [
        "Petrified"
      ]
    },
    {
      "id": "Fragile",
      "name": "Fragile",
      "successRatePercent": 100,
      "description": "Reduces character's defense",
      "statusType": 0,
      "applyMoment": 1,
      "applyType": 3,
      "statName": 5,
      "powerPercent": -30,
      "maxTurns": "3",
      "removesStatusesOnAdd": [
        "Robust"
      ],
      "blockedByStatuses": [
        "Petrified"
      ]
    },
    {
      "id": "Slow",
      "name": "Slow",
      "successRatePercent": 100,
      "description": "Reduces character's speed",
      "statusType": 0,
      "applyMoment": 1,
      "applyType": 3,
      "statName": 8,
      "powerPercent": -30,
      "maxTurns": "3",
      "removesStatusesOnAdd": [
        "Haste"
      ],
      "blockedByStatuses": [
        "Petrified"
      ]
    },
    {
      "id": "Dull",
      "name": "Dull",
      "successRatePercent": 100,
      "description": "Reduces character's intelligence",
      "statusType": 0,
      "applyMoment": 1,
      "applyType": 3,
      "statName": 6,
      "powerPercent": -30,
      "maxTurns": "3",
      "removesStatusesOnAdd": [
        "Focus"
      ],
      "blockedByStatuses": [
        "Petrified"
      ]
    },
    {
      "id": "Weak",
      "name": "Weak",
      "successRatePercent": 100,
      "description": "Reduces character's strength",
      "statusType": 0,
      "applyMoment": 1,
      "applyType": 3,
      "statName": 4,
      "powerPercent": -30,
      "maxTurns": "3",
      "removesStatusesOnAdd": [
        "Strong"
      ],
      "blockedByStatuses": [
        "Petrified"
      ]
    },
    {
      "id": "Light",
      "name": "Light",
      "successRatePercent": 100,
      "description": "Increases character's ability to evade physical attacks",
      "statusType": 1,
      "applyMoment": 1,
      "applyType": 3,
      "statName": 7,
      "powerPercent": 30,
      "maxTurns": "3",
      "removesStatusesOnAdd": [
        "Heavy"
      ],
      "blockedByStatuses": [
        "Petrified"
      ]
    },
    {
      "id": "Robust",
      "name": "Robust",
      "successRatePercent": 100,
      "description": "Increases character's defense",
      "statusType": 1,
      "applyMoment": 1,
      "applyType": 3,
      "statName": 5,
      "powerPercent": 30,
      "maxTurns": "3",
      "removesStatusesOnAdd": [
        "Fragile"
      ],
      "blockedByStatuses": [
        "Petrified"
      ]
    },
    {
      "id": "Haste",
      "name": "Haste",
      "successRatePercent": 100,
      "description": "Increases character's speed",
      "statusType": 1,
      "applyMoment": 1,
      "applyType": 3,
      "statName": 8,
      "powerPercent": 30,
      "maxTurns": "3",
      "removesStatusesOnAdd": [
        "Slow"
      ],
      "blockedByStatuses": [
        "Petrified"
      ]
    },
    {
      "id": "Focus",
      "name": "Focus",
      "successRatePercent": 100,
      "description": "Increases character's intelligence",
      "statusType": 1,
      "applyMoment": 1,
      "applyType": 3,
      "statName": 6,
      "powerPercent": 30,
      "maxTurns": "3",
      "removesStatusesOnAdd": [
        "Dull"
      ],
      "blockedByStatuses": [
        "Petrified"
      ]
    },
    {
      "id": "Strong",
      "name": "Strong",
      "successRatePercent": 100,
      "description": "Increases character's strength",
      "statusType": 1,
      "applyMoment": 1,
      "applyType": 3,
      "statName": 4,
      "powerPercent": 30,
      "maxTurns": "3",
      "removesStatusesOnAdd": [
        "Weak"
      ],
      "blockedByStatuses": [
        "Petrified"
      ]
    },
    {
      "id": "Guard",
      "name": "Guard",
      "successRatePercent": 100,
      "description": "Guard postion doubles the character's defense for the current turn",
      "statusType": 1,
      "applyMoment": 1,
      "applyType": 3,
      "statName": 5,
      "powerPercent": 100,
      "maxTurns": "1"
    }
  ]
}